{
  "user": [
    {
      "first": "Nick Name",
      "email": "Email",
      "password": "Password",
      "passwordRep": "Password Werify",
      "country": "Country",
      "gender": "Gender",
      "age": "Age",
      "parents": "Reptilian Parents",
      "id": 1
    },
    {
      "first": "Patyrk",
      "email": "chodacki.pc@gmail.com",
      "password": "gospodarka",
      "passwordRep": "gospodarka",
      "country": "Polska",
      "gender": "Méæczyznz",
      "age": "28",
      "parents": "true",
      "id": 2
    },
    {
      "first": "Nick Name",
      "email": "Email",
      "password": "dupa",
      "passwordRep": "dupa",
      "country": "Country",
      "gender": "Gender",
      "age": "Age",
      "parents": "Reptilian Parents",
      "id": 3
    },
    {
      "first": "Patryk",
      "last": "Chodacki",
      "email": "chodacki.pc@gmail.com",
      "password": "dupa",
      "passwordRep": "dupa",
      "id": 4
    },
    {
      "first": "",
      "last": "",
      "email": "",
      "password": "",
      "passwordRep": "",
      "id": 5
    },
    {
      "first": "66666",
      "last": "dfgdfg",
      "email": "dfgdfgdg",
      "password": "ggg",
      "passwordRep": "ggg",
      "id": 6
    },
    {
      "first": "",
      "last": "",
      "email": "",
      "password": "",
      "passwordRep": "",
      "id": 7
    },
    {
      "first": "ggg",
      "last": "ggg",
      "email": "ggg",
      "password": "ggg",
      "passwordRep": "ggg",
      "id": 8
    },
    {
      "first": "",
      "last": "",
      "email": "",
      "password": "",
      "passwordRep": "",
      "id": 9
    },
    {
      "first": "",
      "last": "",
      "email": "",
      "password": "",
      "passwordRep": "",
      "id": 10
    },
    {
      "first": "",
      "last": "",
      "email": "",
      "password": "",
      "passwordRep": "",
      "id": 11
    },
    {
      "first": "",
      "last": "",
      "email": "lol",
      "password": "lol",
      "passwordRep": "lol",
      "id": 12
    },
    {
      "first": "Edyta",
      "last": "Chodacka",
      "email": "edyta.chodacka@gmail.com",
      "password": "szarotka",
      "passwordRep": "szarotka",
      "id": 13
    }
  ]
}